colortab.py
colortab-0.1.2.dist-info/METADATA
colortab-0.1.2.dist-info/WHEEL
colortab-0.1.2.dist-info/top_level.txt
colortab-0.1.2.dist-info/RECORD
