Metadata-Version: 2.1
Name: colortab
Version: 0.1.2
Summary: Python-Markdown MkDocs colortab
Home-page: UNKNOWN
Author: beanflame
License: MIT
Keywords: markdown,extensions,mkdocs,plugins,colortab
Platform: UNKNOWN
Requires-Dist: markdown (>=3.0)
